Acoustica/__init__.py
Acoustica/main.py
Disciplina/__init__.py
Disciplina/main.py
Lunastra/__init__.py
Lunastra/main.py
PyAlchemista/__init__.py
PyAlchemista/main.py
Tempore/__init__.py
Tempore/main.py
PyAlchemista-0.0.6.dist-info/LICENSE
PyAlchemista-0.0.6.dist-info/METADATA
PyAlchemista-0.0.6.dist-info/WHEEL
PyAlchemista-0.0.6.dist-info/top_level.txt
PyAlchemista-0.0.6.dist-info/RECORD
