Metadata-Version: 2.1
Name: PyAlchemista
Version: 0.0.6
Summary: A Python library that deals with different fields of science.
Home-page: https://github.com/PyndyalaCoder/PyAlchemista
Author: Siddhu Pendyala
Author-email: elcientifico.pendyala@gmail.com
License: MIT
Project-URL: Bug Tracker, https://github.com/PyndyalaCoder/PyAlchemista/issues
License-File: LICENSE
Requires-Dist: requests
Requires-Dist: matplotlib
Requires-Dist: numpy
Requires-Dist: scipy
